browzy/__init__.py
browzy/core.py
browzy-0.1.1.dist-info/METADATA
browzy-0.1.1.dist-info/WHEEL
browzy-0.1.1.dist-info/entry_points.txt
browzy-0.1.1.dist-info/top_level.txt
browzy-0.1.1.dist-info/RECORD
