Metadata-Version: 2.4
Name: browzy
Version: 0.1.1
Summary: A simple terminal-based web browser with Google search integration
Home-page: https://github.com/QUHu-FER/browzy
Author: QUHU
Author-email: ferdisa321@gmail.com
Keywords: browser terminal web-browser search google cli
Classifier: Programming Language :: Python :: 3
Classifier: License :: OSI Approved :: MIT License
Classifier: Operating System :: OS Independent
Classifier: Environment :: Console
Classifier: Topic :: Internet :: WWW/HTTP :: Browsers
Classifier: Topic :: Internet :: WWW/HTTP :: Dynamic Content
Requires-Python: >=3.6
Requires-Dist: requests
Requires-Dist: beautifulsoup4
Requires-Dist: googlesearch-python
Requires-Dist: colorama
Requires-Dist: pyfiglet
Dynamic: author
Dynamic: author-email
Dynamic: classifier
Dynamic: description
Dynamic: description-content-type
Dynamic: home-page
Dynamic: keywords
Dynamic: requires-dist
Dynamic: requires-python
Dynamic: summary
